rapidocr_pdf/__init__.py
rapidocr_pdf/main.py
rapidocr_pdf/utils/__init__.py
rapidocr_pdf/utils/logger.py
rapidocr_pdf/utils/utils.py
rapidocr_pdf-0.3.0.dist-info/LICENSE
rapidocr_pdf-0.3.0.dist-info/METADATA
rapidocr_pdf-0.3.0.dist-info/WHEEL
rapidocr_pdf-0.3.0.dist-info/entry_points.txt
rapidocr_pdf-0.3.0.dist-info/top_level.txt
rapidocr_pdf-0.3.0.dist-info/RECORD
